{
  "stateName": "North Dakota",
  "stateAbbr": "ND",
  "stateSlug": "north-dakota",
  "stateSeal": null,
  "businessEntitySearch": {
    "cta": "Search North Dakota Business Entities",
    "url": "https://firststop.sos.nd.gov/search/business"
  },
  "secretaryOfState": {
    "agency": "North Dakota Secretary of State - Business Services",
    "officialName": null,
    "website": "https://www.sos.nd.gov/business/business-services",
    "phone": "701-328-2900",
    "email": "business@sos.nd.gov"
  },
  "hours": {
    "timezone": "Central Time",
    "regular": "Monday-Friday, 8:00 a.m.-5:00 p.m.",
    "holidayHours": null
  },
  "physicalAddresses": [
    {
      "label": "Office of the Secretary of State",
      "street": "600 E Boulevard Avenue Dept 108",
      "city": "Bismarck",
      "state": "ND",
      "zip": "58505",
      "country": "USA"
    }
  ],
  "mailingAddress": {
    "street": "600 E Boulevard Avenue Dept 108",
    "city": "Bismarck",
    "state": "ND",
    "zip": "58505",
    "country": "USA"
  },
  "renewals": {
    "onlineRenewalUrl": "https://firststop.sos.nd.gov/",
    "paperRenewalUrl": null,
    "notes": "Most North Dakota business registrations and maintenance filings, including annual reports, are completed through the FirstStop Portal. Business LLC annual reports are due November 15; fee $50."
  },
  "corporateDocuments": {
    "operatingAgreement": null,
    "bylaws": null,
    "otherTemplates": null
  },
  "filingFacts": {
    "llcFee": 135,
    "llcFeeNotes": "Registration fee for domestic and foreign business LLCs is $135 (SOS LLC page).",
    "annualReport": 50,
    "annualReportDue": "Nov 15",
    "nameReservation": 10,
    "nameReservationNotes": "Name reservation is filed through the FirstStop Portal and reserves a name for up to 1 year; the reservation fee is $10 (ND SOS FirstStop, verified 2026-07-23)."
  },
  "sources": [
    {
      "name": "North Dakota LLC fees and annual report requirements",
      "url": "https://www.sos.nd.gov/business/business-services/business-structures/limited-liability-company-llc",
      "lastAccessed": "2026-07-17"
    },
    {
      "name": "North Dakota maintain registration and annual reports",
      "url": "https://www.sos.nd.gov/business/business-services/maintain-registration",
      "lastAccessed": "2026-07-17"
    },
    {
      "name": "North Dakota Secretary of State contact",
      "url": "https://www.sos.nd.gov/contact",
      "lastAccessed": "2026-07-17"
    },
    {
      "name": "North Dakota start a business and name reservation",
      "url": "https://www.sos.nd.gov/business/business-services/start-business",
      "lastAccessed": "2026-07-17"
    }
  ],
  "lastVerified": "2026-07-17"
}
